MANIFEST.in
setup.cfg
setup.py
Pyccuracy.egg-info/PKG-INFO
Pyccuracy.egg-info/SOURCES.txt
Pyccuracy.egg-info/dependency_links.txt
Pyccuracy.egg-info/entry_points.txt
Pyccuracy.egg-info/requires.txt
Pyccuracy.egg-info/top_level.txt
pyccuracy/__init__.py
pyccuracy/airspeed.py
pyccuracy/colored_terminal.py
pyccuracy/common.py
pyccuracy/core.py
pyccuracy/errors.py
pyccuracy/fixture.py
pyccuracy/fixture_items.py
pyccuracy/help.py
pyccuracy/hooks.py
pyccuracy/page.py
pyccuracy/parsers.py
pyccuracy/pyccuracy_console.py
pyccuracy/pyccuracy_help.py
pyccuracy/report_parser.py
pyccuracy/result.py
pyccuracy/story_runner.py
pyccuracy/actions/__init__.py
pyccuracy/actions/core/__init__.py
pyccuracy/actions/core/checkbox_actions.py
pyccuracy/actions/core/element_actions.py
pyccuracy/actions/core/image_actions.py
pyccuracy/actions/core/link_actions.py
pyccuracy/actions/core/page_actions.py
pyccuracy/actions/core/radio_actions.py
pyccuracy/actions/core/select_actions.py
pyccuracy/actions/core/table_actions.py
pyccuracy/actions/core/textbox_actions.py
pyccuracy/django/__init__.py
pyccuracy/django/management/__init__.py
pyccuracy/django/management/commands/__init__.py
pyccuracy/django/management/commands/pyccuracy.py
pyccuracy/drivers/__init__.py
pyccuracy/drivers/interface.py
pyccuracy/drivers/core/__init__.py
pyccuracy/drivers/core/selenium_driver.py
pyccuracy/drivers/core/selenium_element_selector.py
pyccuracy/drivers/core/selenium_webdriver.py
pyccuracy/languages/__init__.py
pyccuracy/languages/data/__init__.py
pyccuracy/languages/data/en-us.txt
pyccuracy/languages/data/pt-br.txt
pyccuracy/languages/templates/__init__.py
pyccuracy/languages/templates/en-us/__init__.py
pyccuracy/languages/templates/en-us/driver_error.template
pyccuracy/languages/templates/en-us/invalid_scenario.template
pyccuracy/languages/templates/en-us/noheader.template
pyccuracy/languages/templates/en-us/summary.template
pyccuracy/languages/templates/pt-br/__init__.py
pyccuracy/languages/templates/pt-br/driver_error.template
pyccuracy/languages/templates/pt-br/invalid_scenario.template
pyccuracy/languages/templates/pt-br/noheader.template
pyccuracy/languages/templates/pt-br/summary.template
