Metadata-Version: 1.0
Name: Pyccuracy
Version: 1.2.47
Summary: Pyccuracy is a BDD style Acceptance Testing framework
Home-page: http://www.pyccuracy.org
Author: Pyccuracy team
Author-email: pyccuracy@googlegroups.com
License: OSI
Keywords: Acceptance Testing Accuracy Behavior Driven Development
Platform: UNKNOWN
Classifier: Development Status :: 5 - Production/Stable
Classifier: Intended Audience :: Developers
Classifier: License :: OSI Approved
Classifier: Natural Language :: English
Classifier: Natural Language :: Portuguese (Brazilian)
Classifier: Operating System :: MacOS
Classifier: Operating System :: Microsoft :: Windows
Classifier: Operating System :: POSIX :: Linux
Classifier: Programming Language :: Python :: 2.5
Classifier: Programming Language :: Python :: 2.6
Classifier: Topic :: Software Development :: Quality Assurance
Classifier: Topic :: Software Development :: Testing
